{
    "type": "FeatureCollection",
    "features": [
        {
            "type": "Feature",
            "geometry": {
                "type": "Point",
                "coordinates": [
                    -117.09325,
                    32.630394
                ]
            },
            "properties": {
                "title": "Tacos El Gordo",
                "description": "689 H Street, Chula Vista, CA 91910",
                "marker-size": "large",
                "marker-color": "#f75850",
                "marker-symbol": "restaurant"
            }
        },
        {
            "type": "Feature",
            "geometry": {
                "type": "Point",
                "coordinates": [
                    -117.16212,
                    32.87998
                ]
            },
            "properties": {
                "title": "Rigoberto's Taco Shop",
                "description": "7094 Miramar Rd, San Diego, CA 92121",
                "marker-size": "large",
                "marker-color": "#f75850",
                "marker-symbol": "restaurant"
            }
        },
        {
            "type": "Feature",
            "geometry": {
                "type": "Point",
                "coordinates": [
                    -73.9882,
                    40.721016
                ]
            },
            "properties": {
                "title": "La Margarita",
                "description": "157 Ludlow Street, New York, NY 10002",
                "marker-size": "large",
                "marker-color": "#f75850",
                "marker-symbol": "restaurant"
            }
        },
        {
            "type": "Feature",
            "geometry": {
                "type": "Point",
                "coordinates": [
                    -118.450325,
                    34.071396
                ]
            },
            "properties": {
                "title": "Bruin Plate Residential Restaurant",
                "description": "350 Charles E Young Drive West, Los Angeles, CA 90095",
                "marker-size": "large",
                "marker-color": "#f75850",
                "marker-symbol": "restaurant"
            }
        }
    ]
}